setup.py
autowsgiserver/__init__.py
autowsgiserver/apps.py
autowsgiserver/context.py
autowsgiserver/info.py
autowsgiserver.egg-info/PKG-INFO
autowsgiserver.egg-info/SOURCES.txt
autowsgiserver.egg-info/dependency_links.txt
autowsgiserver.egg-info/entry_points.txt
autowsgiserver.egg-info/requires.txt
autowsgiserver.egg-info/top_level.txt
autowsgiserver.egg-info/zip-safe