Metadata-Version: 1.0
Name: autowsgiserver
Version: 0.1.26
Summary: autowsgiserver v. 0.1.25
